timeseries_etl_utils/__init__.py
timeseries_etl_utils/utils.py
timeseries_etl_utils-0.0.2.dist-info/LICENSE
timeseries_etl_utils-0.0.2.dist-info/METADATA
timeseries_etl_utils-0.0.2.dist-info/WHEEL
timeseries_etl_utils-0.0.2.dist-info/top_level.txt
timeseries_etl_utils-0.0.2.dist-info/RECORD
