Metadata-Version: 2.1
Name: timeseries-etl-utils
Version: 0.0.2
Summary: Utility functions to create features from timeseries data
License-File: LICENSE
Requires-Dist: numpy
Requires-Dist: pandas
Requires-Dist: openpyxl
Requires-Dist: xlsxwriter
Provides-Extra: dev
Requires-Dist: mypy ; extra == 'dev'
Provides-Extra: test
Requires-Dist: pytest ; extra == 'test'
